{
    "name": "Global Information",
    "numberOfRequests": {
        "total": 5010,
        "ok": 5009,
        "ko": 1
    },
    "minResponseTime": {
        "total": 71,
        "ok": 71,
        "ko": 2163
    },
    "maxResponseTime": {
        "total": 6144,
        "ok": 6144,
        "ko": 2163
    },
    "meanResponseTime": {
        "total": 636,
        "ok": 636,
        "ko": 2163
    },
    "standardDeviation": {
        "total": 540,
        "ok": 540,
        "ko": 0
    },
    "percentiles1": {
        "total": 495,
        "ok": 495,
        "ko": 2163
    },
    "percentiles2": {
        "total": 874,
        "ok": 874,
        "ko": 2163
    },
    "percentiles3": {
        "total": 1594,
        "ok": 1593,
        "ko": 2163
    },
    "percentiles4": {
        "total": 2642,
        "ok": 2642,
        "ko": 2163
    },
    "group1": {
    "name": "t < 800 ms",
    "count": 3527,
    "percentage": 70
},
    "group2": {
    "name": "800 ms < t < 1200 ms",
    "count": 887,
    "percentage": 18
},
    "group3": {
    "name": "t > 1200 ms",
    "count": 595,
    "percentage": 12
},
    "group4": {
    "name": "failed",
    "count": 1,
    "percentage": 0
},
    "meanNumberOfRequestsPerSecond": {
        "total": 5.957193816884661,
        "ok": 5.956004756242568,
        "ko": 0.0011890606420927466
    }
}