{
  "type": "GROUP",
"name": "Global Information",
"path": "",
"pathFormatted": "group_missing-name-b06d1",
"stats": {
    "name": "Global Information",
    "numberOfRequests": {
        "total": 10020,
        "ok": 10014,
        "ko": 6
    },
    "minResponseTime": {
        "total": 66,
        "ok": 66,
        "ko": 2309
    },
    "maxResponseTime": {
        "total": 10006,
        "ok": 7267,
        "ko": 10006
    },
    "meanResponseTime": {
        "total": 810,
        "ok": 806,
        "ko": 8060
    },
    "standardDeviation": {
        "total": 723,
        "ok": 697,
        "ko": 2952
    },
    "percentiles1": {
        "total": 644,
        "ok": 643,
        "ko": 10003
    },
    "percentiles2": {
        "total": 1156,
        "ok": 1155,
        "ko": 10006
    },
    "percentiles3": {
        "total": 2007,
        "ok": 2000,
        "ko": 10006
    },
    "percentiles4": {
        "total": 2993,
        "ok": 2927,
        "ko": 10006
    },
    "group1": {
    "name": "t < 800 ms",
    "count": 5883,
    "percentage": 59
},
    "group2": {
    "name": "800 ms < t < 1200 ms",
    "count": 1812,
    "percentage": 18
},
    "group3": {
    "name": "t > 1200 ms",
    "count": 2319,
    "percentage": 23
},
    "group4": {
    "name": "failed",
    "count": 6,
    "percentage": 0
},
    "meanNumberOfRequestsPerSecond": {
        "total": 6.54046997389034,
        "ok": 6.5365535248041775,
        "ko": 0.0039164490861618795
    }
},
"contents": {
"group_authenticate-ea80a": {
          "type": "GROUP",
"name": "Authenticate",
"path": "Authenticate",
"pathFormatted": "group_authenticate-ea80a",
"stats": {
    "name": "Authenticate",
    "numberOfRequests": {
        "total": 20,
        "ok": 20,
        "ko": 0
    },
    "minResponseTime": {
        "total": 248,
        "ok": 248,
        "ko": 0
    },
    "maxResponseTime": {
        "total": 1457,
        "ok": 1457,
        "ko": 0
    },
    "meanResponseTime": {
        "total": 422,
        "ok": 422,
        "ko": 0
    },
    "standardDeviation": {
        "total": 310,
        "ok": 310,
        "ko": 0
    },
    "percentiles1": {
        "total": 276,
        "ok": 276,
        "ko": 0
    },
    "percentiles2": {
        "total": 381,
        "ok": 381,
        "ko": 0
    },
    "percentiles3": {
        "total": 1040,
        "ok": 1040,
        "ko": 0
    },
    "percentiles4": {
        "total": 1374,
        "ok": 1374,
        "ko": 0
    },
    "group1": {
    "name": "t < 800 ms",
    "count": 17,
    "percentage": 85
},
    "group2": {
    "name": "800 ms < t < 1200 ms",
    "count": 2,
    "percentage": 10
},
    "group3": {
    "name": "t > 1200 ms",
    "count": 1,
    "percentage": 5
},
    "group4": {
    "name": "failed",
    "count": 0,
    "percentage": 0
},
    "meanNumberOfRequestsPerSecond": {
        "total": 0.013054830287206266,
        "ok": 0.013054830287206266,
        "ko": 0
    }
},
"contents": {
"req_authenticate-ea80a": {
        "type": "REQUEST",
        "name": "Authenticate",
"path": "Authenticate / Authenticate",
"pathFormatted": "req_authenticate----de80c",
"stats": {
    "name": "Authenticate",
    "numberOfRequests": {
        "total": 20,
        "ok": 20,
        "ko": 0
    },
    "minResponseTime": {
        "total": 248,
        "ok": 248,
        "ko": 0
    },
    "maxResponseTime": {
        "total": 1457,
        "ok": 1457,
        "ko": 0
    },
    "meanResponseTime": {
        "total": 422,
        "ok": 422,
        "ko": 0
    },
    "standardDeviation": {
        "total": 310,
        "ok": 310,
        "ko": 0
    },
    "percentiles1": {
        "total": 276,
        "ok": 276,
        "ko": 0
    },
    "percentiles2": {
        "total": 381,
        "ok": 381,
        "ko": 0
    },
    "percentiles3": {
        "total": 1040,
        "ok": 1040,
        "ko": 0
    },
    "percentiles4": {
        "total": 1374,
        "ok": 1374,
        "ko": 0
    },
    "group1": {
    "name": "t < 800 ms",
    "count": 17,
    "percentage": 85
},
    "group2": {
    "name": "800 ms < t < 1200 ms",
    "count": 2,
    "percentage": 10
},
    "group3": {
    "name": "t > 1200 ms",
    "count": 1,
    "percentage": 5
},
    "group4": {
    "name": "failed",
    "count": 0,
    "percentage": 0
},
    "meanNumberOfRequestsPerSecond": {
        "total": 0.013054830287206266,
        "ok": 0.013054830287206266,
        "ko": 0
    }
}
    }
}

     },"group_getstarnote-bbf4e": {
          "type": "GROUP",
"name": "GetStarNote",
"path": "GetStarNote",
"pathFormatted": "group_getstarnote-bbf4e",
"stats": {
    "name": "GetStarNote",
    "numberOfRequests": {
        "total": 2000,
        "ok": 1996,
        "ko": 4
    },
    "minResponseTime": {
        "total": 132,
        "ok": 132,
        "ko": 2309
    },
    "maxResponseTime": {
        "total": 10006,
        "ok": 7267,
        "ko": 10006
    },
    "meanResponseTime": {
        "total": 596,
        "ok": 583,
        "ko": 7089
    },
    "standardDeviation": {
        "total": 975,
        "ok": 920,
        "ko": 3201
    },
    "percentiles1": {
        "total": 338,
        "ok": 338,
        "ko": 8020
    },
    "percentiles2": {
        "total": 474,
        "ok": 473,
        "ko": 10005
    },
    "percentiles3": {
        "total": 2277,
        "ok": 2138,
        "ko": 10006
    },
    "percentiles4": {
        "total": 5453,
        "ok": 5424,
        "ko": 10006
    },
    "group1": {
    "name": "t < 800 ms",
    "count": 1778,
    "percentage": 89
},
    "group2": {
    "name": "800 ms < t < 1200 ms",
    "count": 74,
    "percentage": 4
},
    "group3": {
    "name": "t > 1200 ms",
    "count": 144,
    "percentage": 7
},
    "group4": {
    "name": "failed",
    "count": 4,
    "percentage": 0
},
    "meanNumberOfRequestsPerSecond": {
        "total": 1.3054830287206267,
        "ok": 1.3028720626631853,
        "ko": 0.0026109660574412533
    }
},
"contents": {
"req_getstarnote-bbf4e": {
        "type": "REQUEST",
        "name": "GetStarNote",
"path": "GetStarNote / GetStarNote",
"pathFormatted": "req_getstarnote---g-05710",
"stats": {
    "name": "GetStarNote",
    "numberOfRequests": {
        "total": 2000,
        "ok": 1996,
        "ko": 4
    },
    "minResponseTime": {
        "total": 132,
        "ok": 132,
        "ko": 2309
    },
    "maxResponseTime": {
        "total": 10006,
        "ok": 7267,
        "ko": 10006
    },
    "meanResponseTime": {
        "total": 596,
        "ok": 583,
        "ko": 7089
    },
    "standardDeviation": {
        "total": 975,
        "ok": 920,
        "ko": 3201
    },
    "percentiles1": {
        "total": 338,
        "ok": 338,
        "ko": 8020
    },
    "percentiles2": {
        "total": 474,
        "ok": 473,
        "ko": 10005
    },
    "percentiles3": {
        "total": 2277,
        "ok": 2138,
        "ko": 10006
    },
    "percentiles4": {
        "total": 5453,
        "ok": 5424,
        "ko": 10006
    },
    "group1": {
    "name": "t < 800 ms",
    "count": 1779,
    "percentage": 89
},
    "group2": {
    "name": "800 ms < t < 1200 ms",
    "count": 73,
    "percentage": 4
},
    "group3": {
    "name": "t > 1200 ms",
    "count": 144,
    "percentage": 7
},
    "group4": {
    "name": "failed",
    "count": 4,
    "percentage": 0
},
    "meanNumberOfRequestsPerSecond": {
        "total": 1.3054830287206267,
        "ok": 1.3028720626631853,
        "ko": 0.0026109660574412533
    }
}
    }
}

     },"group_getepisodeofcar-15315": {
          "type": "GROUP",
"name": "GetEpisodeOfCare",
"path": "GetEpisodeOfCare",
"pathFormatted": "group_getepisodeofcar-15315",
"stats": {
    "name": "GetEpisodeOfCare",
    "numberOfRequests": {
        "total": 2000,
        "ok": 1999,
        "ko": 1
    },
    "minResponseTime": {
        "total": 368,
        "ok": 368,
        "ko": 10001
    },
    "maxResponseTime": {
        "total": 10001,
        "ok": 2649,
        "ko": 10001
    },
    "meanResponseTime": {
        "total": 922,
        "ok": 918,
        "ko": 10001
    },
    "standardDeviation": {
        "total": 482,
        "ok": 437,
        "ko": 0
    },
    "percentiles1": {
        "total": 816,
        "ok": 816,
        "ko": 10001
    },
    "percentiles2": {
        "total": 1224,
        "ok": 1222,
        "ko": 10001
    },
    "percentiles3": {
        "total": 1753,
        "ok": 1752,
        "ko": 10001
    },
    "percentiles4": {
        "total": 2119,
        "ok": 2094,
        "ko": 10001
    },
    "group1": {
    "name": "t < 800 ms",
    "count": 975,
    "percentage": 49
},
    "group2": {
    "name": "800 ms < t < 1200 ms",
    "count": 510,
    "percentage": 26
},
    "group3": {
    "name": "t > 1200 ms",
    "count": 514,
    "percentage": 26
},
    "group4": {
    "name": "failed",
    "count": 1,
    "percentage": 0
},
    "meanNumberOfRequestsPerSecond": {
        "total": 1.3054830287206267,
        "ok": 1.3048302872062663,
        "ko": 6.527415143603133E-4
    }
},
"contents": {
"req_getepisodeofcar-15315": {
        "type": "REQUEST",
        "name": "GetEpisodeOfCare",
"path": "GetEpisodeOfCare / GetEpisodeOfCare",
"pathFormatted": "req_getepisodeofcar-3d623",
"stats": {
    "name": "GetEpisodeOfCare",
    "numberOfRequests": {
        "total": 2000,
        "ok": 1999,
        "ko": 1
    },
    "minResponseTime": {
        "total": 368,
        "ok": 368,
        "ko": 10001
    },
    "maxResponseTime": {
        "total": 10001,
        "ok": 2649,
        "ko": 10001
    },
    "meanResponseTime": {
        "total": 922,
        "ok": 918,
        "ko": 10001
    },
    "standardDeviation": {
        "total": 482,
        "ok": 437,
        "ko": 0
    },
    "percentiles1": {
        "total": 816,
        "ok": 816,
        "ko": 10001
    },
    "percentiles2": {
        "total": 1224,
        "ok": 1222,
        "ko": 10001
    },
    "percentiles3": {
        "total": 1753,
        "ok": 1752,
        "ko": 10001
    },
    "percentiles4": {
        "total": 2119,
        "ok": 2094,
        "ko": 10001
    },
    "group1": {
    "name": "t < 800 ms",
    "count": 976,
    "percentage": 49
},
    "group2": {
    "name": "800 ms < t < 1200 ms",
    "count": 509,
    "percentage": 25
},
    "group3": {
    "name": "t > 1200 ms",
    "count": 514,
    "percentage": 26
},
    "group4": {
    "name": "failed",
    "count": 1,
    "percentage": 0
},
    "meanNumberOfRequestsPerSecond": {
        "total": 1.3054830287206267,
        "ok": 1.3048302872062663,
        "ko": 6.527415143603133E-4
    }
}
    }
}

     },"group_getstaruimember-78052": {
          "type": "GROUP",
"name": "GetStarUIMemberList",
"path": "GetStarUIMemberList",
"pathFormatted": "group_getstaruimember-78052",
"stats": {
    "name": "GetStarUIMemberList",
    "numberOfRequests": {
        "total": 2000,
        "ok": 2000,
        "ko": 0
    },
    "minResponseTime": {
        "total": 670,
        "ok": 670,
        "ko": 0
    },
    "maxResponseTime": {
        "total": 3628,
        "ok": 3628,
        "ko": 0
    },
    "meanResponseTime": {
        "total": 1392,
        "ok": 1392,
        "ko": 0
    },
    "standardDeviation": {
        "total": 532,
        "ok": 532,
        "ko": 0
    },
    "percentiles1": {
        "total": 1289,
        "ok": 1289,
        "ko": 0
    },
    "percentiles2": {
        "total": 1740,
        "ok": 1740,
        "ko": 0
    },
    "percentiles3": {
        "total": 2371,
        "ok": 2371,
        "ko": 0
    },
    "percentiles4": {
        "total": 2812,
        "ok": 2812,
        "ko": 0
    },
    "group1": {
    "name": "t < 800 ms",
    "count": 232,
    "percentage": 12
},
    "group2": {
    "name": "800 ms < t < 1200 ms",
    "count": 659,
    "percentage": 33
},
    "group3": {
    "name": "t > 1200 ms",
    "count": 1109,
    "percentage": 55
},
    "group4": {
    "name": "failed",
    "count": 0,
    "percentage": 0
},
    "meanNumberOfRequestsPerSecond": {
        "total": 1.3054830287206267,
        "ok": 1.3054830287206267,
        "ko": 0
    }
},
"contents": {
"req_getstaruimember-78052": {
        "type": "REQUEST",
        "name": "GetStarUIMemberList",
"path": "GetStarUIMemberList / GetStarUIMemberList",
"pathFormatted": "req_getstaruimember-65cb3",
"stats": {
    "name": "GetStarUIMemberList",
    "numberOfRequests": {
        "total": 2000,
        "ok": 2000,
        "ko": 0
    },
    "minResponseTime": {
        "total": 670,
        "ok": 670,
        "ko": 0
    },
    "maxResponseTime": {
        "total": 3628,
        "ok": 3628,
        "ko": 0
    },
    "meanResponseTime": {
        "total": 1392,
        "ok": 1392,
        "ko": 0
    },
    "standardDeviation": {
        "total": 532,
        "ok": 532,
        "ko": 0
    },
    "percentiles1": {
        "total": 1289,
        "ok": 1289,
        "ko": 0
    },
    "percentiles2": {
        "total": 1740,
        "ok": 1740,
        "ko": 0
    },
    "percentiles3": {
        "total": 2371,
        "ok": 2371,
        "ko": 0
    },
    "percentiles4": {
        "total": 2812,
        "ok": 2812,
        "ko": 0
    },
    "group1": {
    "name": "t < 800 ms",
    "count": 232,
    "percentage": 12
},
    "group2": {
    "name": "800 ms < t < 1200 ms",
    "count": 659,
    "percentage": 33
},
    "group3": {
    "name": "t > 1200 ms",
    "count": 1109,
    "percentage": 55
},
    "group4": {
    "name": "failed",
    "count": 0,
    "percentage": 0
},
    "meanNumberOfRequestsPerSecond": {
        "total": 1.3054830287206267,
        "ok": 1.3054830287206267,
        "ko": 0
    }
}
    }
}

     },"group_getstaruimember-15c8b": {
          "type": "GROUP",
"name": "GetStarUIMemberDetail",
"path": "GetStarUIMemberDetail",
"pathFormatted": "group_getstaruimember-15c8b",
"stats": {
    "name": "GetStarUIMemberDetail",
    "numberOfRequests": {
        "total": 2000,
        "ok": 2000,
        "ko": 0
    },
    "minResponseTime": {
        "total": 369,
        "ok": 369,
        "ko": 0
    },
    "maxResponseTime": {
        "total": 3551,
        "ok": 3551,
        "ko": 0
    },
    "meanResponseTime": {
        "total": 925,
        "ok": 925,
        "ko": 0
    },
    "standardDeviation": {
        "total": 453,
        "ok": 453,
        "ko": 0
    },
    "percentiles1": {
        "total": 827,
        "ok": 827,
        "ko": 0
    },
    "percentiles2": {
        "total": 1200,
        "ok": 1200,
        "ko": 0
    },
    "percentiles3": {
        "total": 1787,
        "ok": 1787,
        "ko": 0
    },
    "percentiles4": {
        "total": 2249,
        "ok": 2249,
        "ko": 0
    },
    "group1": {
    "name": "t < 800 ms",
    "count": 965,
    "percentage": 48
},
    "group2": {
    "name": "800 ms < t < 1200 ms",
    "count": 535,
    "percentage": 27
},
    "group3": {
    "name": "t > 1200 ms",
    "count": 500,
    "percentage": 25
},
    "group4": {
    "name": "failed",
    "count": 0,
    "percentage": 0
},
    "meanNumberOfRequestsPerSecond": {
        "total": 1.3054830287206267,
        "ok": 1.3054830287206267,
        "ko": 0
    }
},
"contents": {
"req_getstaruimember-15c8b": {
        "type": "REQUEST",
        "name": "GetStarUIMemberDetail",
"path": "GetStarUIMemberDetail / GetStarUIMemberDetail",
"pathFormatted": "req_getstaruimember-e0069",
"stats": {
    "name": "GetStarUIMemberDetail",
    "numberOfRequests": {
        "total": 2000,
        "ok": 2000,
        "ko": 0
    },
    "minResponseTime": {
        "total": 369,
        "ok": 369,
        "ko": 0
    },
    "maxResponseTime": {
        "total": 3551,
        "ok": 3551,
        "ko": 0
    },
    "meanResponseTime": {
        "total": 925,
        "ok": 925,
        "ko": 0
    },
    "standardDeviation": {
        "total": 453,
        "ok": 453,
        "ko": 0
    },
    "percentiles1": {
        "total": 827,
        "ok": 827,
        "ko": 0
    },
    "percentiles2": {
        "total": 1200,
        "ok": 1200,
        "ko": 0
    },
    "percentiles3": {
        "total": 1787,
        "ok": 1787,
        "ko": 0
    },
    "percentiles4": {
        "total": 2249,
        "ok": 2249,
        "ko": 0
    },
    "group1": {
    "name": "t < 800 ms",
    "count": 965,
    "percentage": 48
},
    "group2": {
    "name": "800 ms < t < 1200 ms",
    "count": 535,
    "percentage": 27
},
    "group3": {
    "name": "t > 1200 ms",
    "count": 500,
    "percentage": 25
},
    "group4": {
    "name": "failed",
    "count": 0,
    "percentage": 0
},
    "meanNumberOfRequestsPerSecond": {
        "total": 1.3054830287206267,
        "ok": 1.3054830287206267,
        "ko": 0
    }
}
    }
}

     },"group_chattranscript-17d72": {
          "type": "GROUP",
"name": "ChatTranscript",
"path": "ChatTranscript",
"pathFormatted": "group_chattranscript-17d72",
"stats": {
    "name": "ChatTranscript",
    "numberOfRequests": {
        "total": 2000,
        "ok": 1999,
        "ko": 1
    },
    "minResponseTime": {
        "total": 66,
        "ok": 66,
        "ko": 10006
    },
    "maxResponseTime": {
        "total": 10006,
        "ok": 5065,
        "ko": 10006
    },
    "meanResponseTime": {
        "total": 222,
        "ok": 217,
        "ko": 10006
    },
    "standardDeviation": {
        "total": 433,
        "ok": 374,
        "ko": 0
    },
    "percentiles1": {
        "total": 88,
        "ok": 88,
        "ko": 10006
    },
    "percentiles2": {
        "total": 254,
        "ok": 254,
        "ko": 10006
    },
    "percentiles3": {
        "total": 738,
        "ok": 737,
        "ko": 10006
    },
    "percentiles4": {
        "total": 2016,
        "ok": 2005,
        "ko": 10006
    },
    "group1": {
    "name": "t < 800 ms",
    "count": 1914,
    "percentage": 96
},
    "group2": {
    "name": "800 ms < t < 1200 ms",
    "count": 34,
    "percentage": 2
},
    "group3": {
    "name": "t > 1200 ms",
    "count": 51,
    "percentage": 3
},
    "group4": {
    "name": "failed",
    "count": 1,
    "percentage": 0
},
    "meanNumberOfRequestsPerSecond": {
        "total": 1.3054830287206267,
        "ok": 1.3048302872062663,
        "ko": 6.527415143603133E-4
    }
},
"contents": {
"req_chattranscript-17d72": {
        "type": "REQUEST",
        "name": "ChatTranscript",
"path": "ChatTranscript / ChatTranscript",
"pathFormatted": "req_chattranscript--000e3",
"stats": {
    "name": "ChatTranscript",
    "numberOfRequests": {
        "total": 2000,
        "ok": 1999,
        "ko": 1
    },
    "minResponseTime": {
        "total": 66,
        "ok": 66,
        "ko": 10006
    },
    "maxResponseTime": {
        "total": 10006,
        "ok": 5065,
        "ko": 10006
    },
    "meanResponseTime": {
        "total": 222,
        "ok": 217,
        "ko": 10006
    },
    "standardDeviation": {
        "total": 433,
        "ok": 374,
        "ko": 0
    },
    "percentiles1": {
        "total": 88,
        "ok": 88,
        "ko": 10006
    },
    "percentiles2": {
        "total": 254,
        "ok": 254,
        "ko": 10006
    },
    "percentiles3": {
        "total": 738,
        "ok": 737,
        "ko": 10006
    },
    "percentiles4": {
        "total": 2016,
        "ok": 2005,
        "ko": 10006
    },
    "group1": {
    "name": "t < 800 ms",
    "count": 1914,
    "percentage": 96
},
    "group2": {
    "name": "800 ms < t < 1200 ms",
    "count": 34,
    "percentage": 2
},
    "group3": {
    "name": "t > 1200 ms",
    "count": 51,
    "percentage": 3
},
    "group4": {
    "name": "failed",
    "count": 1,
    "percentage": 0
},
    "meanNumberOfRequestsPerSecond": {
        "total": 1.3054830287206267,
        "ok": 1.3048302872062663,
        "ko": 6.527415143603133E-4
    }
}
    }
}

     }
}

}